Jellyfin_CLI-1.6.data/scripts/jellyfin-cli
jellyfin_cli/__init__.py
jellyfin_cli/main.py
jellyfin_cli/jellyfin_client/JellyfinClient.py
jellyfin_cli/jellyfin_client/__init__.py
jellyfin_cli/jellyfin_client/data_classes/Audio.py
jellyfin_cli/jellyfin_client/data_classes/Items.py
jellyfin_cli/jellyfin_client/data_classes/Movies.py
jellyfin_cli/jellyfin_client/data_classes/Shows.py
jellyfin_cli/jellyfin_client/data_classes/View.py
jellyfin_cli/jellyfin_client/data_classes/__init__.py
jellyfin_cli/urwid_overrides/Button.py
jellyfin_cli/urwid_overrides/__init__.py
jellyfin_cli/utils/__init__.py
jellyfin_cli/utils/login_helper.py
jellyfin_cli/utils/play_utils.py
Jellyfin_CLI-1.6.dist-info/LICENSE
Jellyfin_CLI-1.6.dist-info/METADATA
Jellyfin_CLI-1.6.dist-info/WHEEL
Jellyfin_CLI-1.6.dist-info/entry_points.txt
Jellyfin_CLI-1.6.dist-info/top_level.txt
Jellyfin_CLI-1.6.dist-info/RECORD
