Metadata-Version: 2.1
Name: Jellyfin-CLI
Version: 1.6
Summary: A Jellyfin command line client.
Home-page: https://github.com/marios8543/Jellyfin-CLI
Author: marios8543
Author-email: marios8543@gmail.com
License: UNKNOWN
Platform: UNKNOWN
Classifier: Programming Language :: Python :: 3
Classifier: License :: OSI Approved :: MIT License
Classifier: Operating System :: OS Independent
License-File: LICENSE
Requires-Dist: aiohttp
Requires-Dist: urwid
Requires-Dist: aio-mpv-jsonipc
